upstream_edge/__init__.py
upstream_edge-0.0.0.dist-info/METADATA
upstream_edge-0.0.0.dist-info/WHEEL
upstream_edge-0.0.0.dist-info/top_level.txt
upstream_edge-0.0.0.dist-info/RECORD
