Metadata-Version: 2.1
Name: upstream_edge
Version: 0.0.0
Summary: Upstream Edge Python Utilities
Classifier: Development Status :: 1 - Planning
Classifier: Programming Language :: Python :: 3
Classifier: Programming Language :: Python :: 3.10
Classifier: Programming Language :: Python :: 3.11
Requires-Python: >=3.10
